labelbox/__init__.py
labelbox/adv_client.py
labelbox/annotated_types.py
labelbox/client.py
labelbox/pagination.py
labelbox/parser.py
labelbox/project_validation.py
labelbox/types.py
labelbox/utils.py
labelbox/data/__init__.py
labelbox/data/generator.py
labelbox/data/mixins.py
labelbox/data/ontology.py
labelbox/data/annotation_types/__init__.py
labelbox/data/annotation_types/annotation.py
labelbox/data/annotation_types/base_annotation.py
labelbox/data/annotation_types/collection.py
labelbox/data/annotation_types/feature.py
labelbox/data/annotation_types/label.py
labelbox/data/annotation_types/mmc.py
labelbox/data/annotation_types/relationship.py
labelbox/data/annotation_types/temporal.py
labelbox/data/annotation_types/types.py
labelbox/data/annotation_types/video.py
labelbox/data/annotation_types/classification/__init__.py
labelbox/data/annotation_types/classification/classification.py
labelbox/data/annotation_types/data/__init__.py
labelbox/data/annotation_types/data/base_data.py
labelbox/data/annotation_types/data/generic_data_row_data.py
labelbox/data/annotation_types/data/raster.py
labelbox/data/annotation_types/data/tiled_image.py
labelbox/data/annotation_types/geometry/__init__.py
labelbox/data/annotation_types/geometry/geometry.py
labelbox/data/annotation_types/geometry/line.py
labelbox/data/annotation_types/geometry/mask.py
labelbox/data/annotation_types/geometry/point.py
labelbox/data/annotation_types/geometry/polygon.py
labelbox/data/annotation_types/geometry/rectangle.py
labelbox/data/annotation_types/llm_prompt_response/__init__.py
labelbox/data/annotation_types/llm_prompt_response/prompt.py
labelbox/data/annotation_types/metrics/__init__.py
labelbox/data/annotation_types/metrics/base.py
labelbox/data/annotation_types/metrics/confusion_matrix.py
labelbox/data/annotation_types/metrics/scalar.py
labelbox/data/annotation_types/ner/__init__.py
labelbox/data/annotation_types/ner/conversation_entity.py
labelbox/data/annotation_types/ner/document_entity.py
labelbox-7.5.0.dist-info/METADATA
labelbox-7.5.0.dist-info/WHEEL
labelbox-7.5.0.dist-info/RECORD
