Metadata-Version: 2.4
Name: labelbox
Version: 7.5.0
Summary: Labelbox Python API
Project-URL: Homepage, https://labelbox.com/
Project-URL: Documentation, https://labelbox-python.readthedocs.io/en/latest/
Project-URL: Repository, https://github.com/Labelbox/labelbox-python
Project-URL: Issues, https://github.com/Labelbox/labelbox-python/issues
Project-URL: Changelog, https://github.com/Labelbox/labelbox-python/blob/develop/libs/labelbox/CHANGELOG.md
Author-email: Labelbox <engineering@labelbox.com>
Keywords: ai,edu,labelbox,labeling,llm,machinelearning,ml
Classifier: Development Status :: 5 - Production/Stable
Classifier: Intended Audience :: Developers
Classifier: Intended Audience :: Education
Classifier: Intended Audience :: Science/Research
Classifier: License :: OSI Approved :: Apache Software License
Classifier: Programming Language :: Python :: 3
Classifier: Programming Language :: Python :: 3.9
Classifier: Programming Language :: Python :: 3.10
Classifier: Programming Language :: Python :: 3.11
Classifier: Programming Language :: Python :: 3.12
Classifier: Programming Language :: Python :: 3.13
Classifier: Topic :: Scientific/Engineering :: Artificial Intelligence
Classifier: Topic :: Software Development :: Libraries
Requires-Python: <3.14,>=3.9
Requires-Dist: geojson>=3.1.0
Requires-Dist: google-api-core>=1.22.1
Requires-Dist: lbox-clients==1.1.2
Requires-Dist: pydantic>=2.0
Requires-Dist: python-dateutil<2.10.0,>=2.8.2
Requires-Dist: pyyaml>=6.0
Requires-Dist: requests>=2.22.0
Requires-Dist: strenum>=0.4.15
Requires-Dist: tqdm>=4.66.2
Provides-Extra: alignerr
Requires-Dist: lbox-alignerr>=0.1.0; extra == 'alignerr'
Provides-Extra: data
Requires-Dist: imagesize>=1.4.1; extra == 'data'
Requires-Dist: numpy>=1.25.0; extra == 'data'
Requires-Dist: opencv-python-headless>=4.9.0.80; extra == 'data'
Requires-Dist: pillow>=10.2.0; extra == 'data'
Requires-Dist: pygeotile>=1.0.6; extra == 'data'
Requires-Dist: pyproj>=3.5.0; extra == 'data'
Requires-Dist: shapely>=2.0.3; extra == 'data'
Requires-Dist: typeguard>=4.1.5; extra == 'data'
Requires-Dist: typing-extensions>=4.10.0; extra == 'data'
